MANIFEST.in
README.md
VERSION
djangular_cli/__init__.py
djangular_cli/__main__.py
djangular_cli/__version__.py
djangular_cli/djangular.py
djangular_cli/config/__init__.py
djangular_cli/config/app_settings.py
djangular_cli/config/style/__init__.py
djangular_cli/config/style/color_style.py
djangular_cli/config/style/widget.py
djangular_cli/dependencies/__init__.py
djangular_cli/dependencies/django.txt
djangular_cli/dependencies/requirements.txt
djangular_cli/dependencies/update_pip.txt
djangular_cli/docs/CREDITS
djangular_cli/generate/__init__.py
djangular_cli/generate/create.py
djangular_cli/generate/bin/django-admin
djangular_cli/git/__init__.py
djangular_cli/git/git.py
djangular_cli/management/__init__.py
djangular_cli/management/commands.py
djangular_cli/management/exceptions.py
djangular_cli/management/find.py
djangular_cli/management/utils.py
djangular_cli/terminal/__init__.py
djangular_cli/terminal/cli.py
djangular_cli/terminal/color_print.py
djangular_cli/terminal/custom_prompts.py
djangular_cli/terminal/prompt.py
djangular_cli/terminal/separator.py
djangular_cli/terminal/utils.py
djangular_cli/terminal/prompts/__init__.py
djangular_cli/terminal/prompts/checkbox.py
djangular_cli/terminal/prompts/common.py
djangular_cli/terminal/prompts/confirm.py
djangular_cli/terminal/prompts/editor.py
djangular_cli/terminal/prompts/expand.py
djangular_cli/terminal/prompts/input.py
djangular_cli/terminal/prompts/list.py
djangular_cli/terminal/prompts/password.py
djangular_cli/terminal/prompts/rawlist.py
djangular_cli-1.2.4.dev2.data/scripts/django-admin
djangular_cli-1.2.4.dev2.dist-info/METADATA
djangular_cli-1.2.4.dev2.dist-info/WHEEL
djangular_cli-1.2.4.dev2.dist-info/entry_points.txt
djangular_cli-1.2.4.dev2.dist-info/top_level.txt
djangular_cli-1.2.4.dev2.dist-info/RECORD
