Metadata-Version: 2.1
Name: djangular-cli
Version: 1.2.4.dev2
Summary: Django + Angular client for complete project management & development.
Home-page: https://github.com/forafekt/djangular-cli
Author: Jonny Doyle
Author-email: jonathan.d@programmer.net
License: MIT
Project-URL: Bug Tracker, https://github.com/forafekt/djangular-cli/issues
Project-URL: Documentation, https://github.com/forafekt/djangular-cli/tree/master/djangular_cli/docs
Project-URL: Source Code, https://github.com/forafekt/djangular-cli
Keywords: django angular client template boilerplate git automate
Platform: UNKNOWN
Classifier: Programming Language :: Python :: 3
Classifier: License :: OSI Approved :: MIT License
Classifier: Operating System :: OS Independent
Classifier: Intended Audience :: Developers
Classifier: Topic :: Software Development :: Build Tools
Requires-Python: >=3.6
Requires-Dist: prompt-toolkit
Requires-Dist: virtualenv
Requires-Dist: setuptools
Requires-Dist: django-environ
Requires-Dist: pyfiglet
Requires-Dist: pygments
